powder_ens_commons/__init__.py
powder_ens_commons/datacommons/__init__.py
powder_ens_commons/datacommons/loaders.py
powder_ens_commons/datacommons/utils/__init__.py
powder_ens_commons/datacommons/utils/splitter.py
powder_ens_commons/modelcommons/__init__.py
powder_ens_commons/modelcommons/localization_unet_bspline/__init__.py
powder_ens_commons/modelcommons/localization_unet_bspline/attacker.py
powder_ens_commons/modelcommons/localization_unet_bspline/b_spline_silu.py
powder_ens_commons/modelcommons/localization_unet_bspline/b_spline_utils.py
powder_ens_commons/modelcommons/localization_unet_bspline/coordinates.py
powder_ens_commons/modelcommons/localization_unet_bspline/dataset2.py
powder_ens_commons/modelcommons/localization_unet_bspline/localization_bspline2.py
powder_ens_commons/modelcommons/localization_unet_bspline/locconfig.py
powder_ens_commons/modelcommons/localization_unet_bspline/models_bspline2.py
powder_ens_commons/modelcommons/localization_unet_bspline/runner.py
powder_ens_commons-0.3.14.dist-info/METADATA
powder_ens_commons-0.3.14.dist-info/WHEEL
powder_ens_commons-0.3.14.dist-info/top_level.txt
powder_ens_commons-0.3.14.dist-info/RECORD
