Metadata-Version: 2.4
Name: powder_ens_commons
Version: 0.3.14
Summary: A simple data/model commons package for POWDER experiments
Home-page: https://gitlab.flux.utah.edu/mumtahin_habib/powder_ens_commons
Author: Mumtahin Habib
Author-email: mumtahin.mazumder@utah.edu
Classifier: Programming Language :: Python :: 3
Classifier: Operating System :: OS Independent
Requires-Python: >=3.10, <3.13
Requires-Dist: rasterio<1.5,>=1.3.6
Requires-Dist: scipy<1.13,>=1.11
Requires-Dist: torch<2.6,>=2.4.0
Requires-Dist: opencv-python<4.10,>=4.7.0.72
Requires-Dist: shapely<2.1,>=2.0.1
Requires-Dist: scikit-image<0.23,>=0.22.0
Requires-Dist: pandas<2.3,>=2.0.2
Requires-Dist: numpy<2.0,>=1.26
Requires-Dist: matplotlib<3.10,>=3.8.3
Requires-Dist: scikit-learn<1.4,>=1.2.2
Requires-Dist: utm<1.0,>=0.7.0
Requires-Dist: POT<0.10,>=0.9.3
Requires-Dist: sympy<1.13,>=1.12
Requires-Dist: tqdm<4.67,>=4.66.2
Requires-Dist: requests
Dynamic: author
Dynamic: author-email
Dynamic: classifier
Dynamic: home-page
Dynamic: requires-dist
Dynamic: requires-python
Dynamic: summary
